{
	"name": "baketorio_plus", 
	"version": "0.0.5",
	"title": "Baketorio+",
	"author": "Edenstudent",
	"factorio_version": "2.0", 
	"contact": "Edenstudent", 
	"description": "An expansion to the Baketorio overhaul mod. \n\nEnable \"Enable all Feature Flags\" mod if you own the DLC for full features of this mod.\nIf you do so though, Runtime Spoilage Library MUST be installed",
	"dependencies": ["baketorio >= 2.0.14", "? quality", "? enable-all-feature-flags >= 1.0.2", "? Runtime Spoilage Library >= 1.0.2", "! space-age"]
}